blockedonweibo/__init__.py
blockedonweibo/weibo.py
blockedonweibo/weibo_credentials.py
blockedonweibo-0.2.dist-info/DESCRIPTION.rst
blockedonweibo-0.2.dist-info/METADATA
blockedonweibo-0.2.dist-info/RECORD
blockedonweibo-0.2.dist-info/WHEEL
blockedonweibo-0.2.dist-info/metadata.json
blockedonweibo-0.2.dist-info/top_level.txt
