Metadata-Version: 2.0
Name: blockedonweibo
Version: 0.2
Summary: Testing if search keywords are censored on Sina Weibo
Home-page: http://github.com/jasonqng/blocked-on-weibo
Author: Jason Q. Ng
Author-email: jason.q.ng@gmail.com
License: BSD License
Platform: UNKNOWN
